marmot/__init__.py
marmot/client.py
marmot/dataset.py
marmot/proto_utils.py
marmot/record.py
marmot/types.py
marmot_client-1.0.0.dist-info/METADATA
marmot_client-1.0.0.dist-info/WHEEL
marmot_client-1.0.0.dist-info/top_level.txt
marmot_client-1.0.0.dist-info/RECORD
