Metadata-Version: 2.1
Name: marmot-client
Version: 1.0.0
Summary: Python client interface to Marmot
Home-page: https://github.com/kwlee0220/marmot.client.python
Author: Kang-Woo Lee
Author-email: kwlee@etri.re.kr
License: UNKNOWN
Platform: UNKNOWN
Requires-Python: >=3
Requires-Dist: protobuf
Requires-Dist: grpcio
